{
  "id": "dream-motel-echo-weaving-combo",
  "title": "Dream Motel: Echo Loom",
  "description": "3초 잔상으로 스위치와 길을 동시에 여는 드림 모텔 퍼즐 액션",
  "creator": {
    "name": "jungcollin",
    "avatar": null,
    "github": "jungcollin"
  },
  "genre": "Echo puzzler / 콤보 임계치",
  "clearCondition": "콤보를 유지하며 모든 코어 문양을 연결하면 클리어",
  "failCondition": "콤보가 여러 번 끊기거나 잔상 선이 끊기면 즉시 실패",
  "controls": "마우스 또는 터치 드래그로 실 배치, 클릭 또는 터치 홀드로 잔상 기록, 연속 성공이 끊기지 않게 안전 루트 유지, 모바일에서는 화면 터치와 드래그만으로도 플레이 가능하게 구현",
  "estimatedSeconds": null
}
